clocksays/__init__.py
clocksays/saytime.py
clocksays/start.py
clocksays-0.2.1.dist-info/METADATA
clocksays-0.2.1.dist-info/WHEEL
clocksays-0.2.1.dist-info/entry_points.txt
clocksays-0.2.1.dist-info/licenses/LICENSE
clocksays-0.2.1.dist-info/RECORD
