Metadata-Version: 2.3
Name: clocksays
Version: 0.2.1
Summary: Add your description here
Author-email: Gerrit Kocherscheidt <kochersg@koco-group.com>
License-File: LICENSE
Requires-Python: >=3.8
